Lab8_Digital1/Ejercicio2-ROM/ROM.v
// Luis Pedro Molina Velásquez
// Carné 18822 - Sección 12
// Laboratorio 8 
// Ejercicio 2 - Memoria ROM

module MROM (input wire [11:0]Lectura, output wire [7:0]Datos);  

    reg [7:0] Memoria_ROM[0:4095];

    initial begin 
        $readmemb("memoria.listLP", Memoria_ROM);
    end

    assign Datos = Memoria_ROM[Lectura];

endmodule

Lab8_Digital1/Ejercicio2-ROM/ROM_tb.v
// Luis Pedro Molina Velásquez
// Carné 18822 - Sección 12
// Laboratorio 8 
// Ejercicio 2 - Memoria ROM

module testbench ();

reg [11:0]Lectura;
wire [7:0]Datos;

MROM M_R (Lectura, Datos);

initial begin
    
    #1
    $display(" ");
    $display(" Memoria ROM ");
    $display(" ");
    $display(" Espacio       |   Lectura   ");
    $display("--------------|-------------");
    $monitor("%b     ", Lectura, Datos);
       Lectura = 12'b000000000000 ;
    #1 Lectura = 12'b000000000000 ; // 0
    #1 Lectura = 12'b000000000001 ;
    #1 Lectura = 12'b000000000010 ;
    #1 Lectura = 12'b000000000011 ;
    #1 Lectura = 12'b000000000100 ;
    #1 Lectura = 12'b000000000101 ; // 5
    #1 Lectura = 12'b000000000110 ;
    #1 Lectura = 12'b000000000111 ;
    #1 Lectura = 12'b000000001000 ;
    #1 Lectura = 12'b000000001001 ;
    #1 Lectura = 12'b000000001010 ;  // 10

end

    initial 
    #30 $finish;

initial 
    begin
        $dumpfile("ROM_tb.vcd");
        $dumpvars(0,testbench);
    end

endmodule

Lab8_Digital1/Ejercicio2-ROM/ROM_tb.vcd
$date
	Sat Oct 24 23:23:50 2020
$end
$version
	Icarus Verilog
$end
$timescale
	1ps
$end
$scope module testbench $end
$var wire 8 ! Datos [7:0] $end
$var reg 12 " Lectura [11:0] $end
$scope module M_R $end
$var wire 8 # Datos [7:0] $end
$var wire 12 $ Lectura [11:0] $end
$upscope $end
$upscope $end
$enddefinitions $end
#0
$dumpvars
bx $
bx #
bx "
bx !
$end
#1
b10010001 !
b10010001 #
b0 "
b0 $
#3
b11 !
b11 #
b1 "
b1 $
#4
b1001100 !
b1001100 #
b10 "
b10 $
#5
b11011011 !
b11011011 #
b11 "
b11 $
#6
b1 !
b1 #
b100 "
b100 $
#7
b10111111 !
b10111111 #
b101 "
b101 $
#8
b11110000 !
b11110000 #
b110 "
b110 $
#9
b10101010 !
b10101010 #
b111 "
b111 $
#10
b1010111 !
b1010111 #
b1000 "
b1000 $
#11
b11000011 !
b11000011 #
b1001 "
b1001 $
#12
bx !
bx #
b1010 "
b1010 $
