Lab8_Digital1/Ejercicio1-Counter/counter.v
// Luis Pedro Molina Velásquez
// Carné 18822 - Sección 12
// Laboratorio 8 
// Ejercicio 1 - Contador de 12 bits

module counter (input wire clk, ENABLE, reset, nonblck, input wire [11:0]LOAD, output reg [11:0]Q);

    always @ (posedge clk  or posedge reset or posedge nonblck)begin
        if (reset == 1)
            Q <= 12'b000000000000;

        else if (ENABLE == 1)
            Q <= (Q + 1);

        else if (nonblck == 1)
            Q <= LOAD;
    end

endmodule

Lab8_Digital1/Ejercicio1-Counter/counter_tb.v
// Luis Pedro Molina Velásquez
// Carné 18822 - Sección 12
// Laboratorio 8 
// Ejercicio 1 - Contador de 12 bits

module testbench ();

reg clk, ENABLE, reset, nonblck ;
reg [11:0]LOAD;
wire[11:0]Q ;

counter CONT (clk, ENABLE, reset, nonblck, LOAD, Q);


initial begin
    clk=1;
    forever #1 clk = ~clk;
end

    initial begin

        #1
        $display(" ");
        $display(" Contador de 12 bits");
        $display("");
        $display("\t\t Time \tclk  \t E  \tRst   \tN-B | \tContador");       // Se utilizo \t para que el texto y los valores estuvieran tabulados.
        $display("------------------------------------|------------");
        $monitor("%d  \t %d     \t %b   \t %b  \t %b   \t %d", $time, clk, ENABLE, reset, nonblck, Q);   // Se utilizo \t para que el texto y los valores estuvieran tabulados.
        clk = 0 ; reset = 0 ; ENABLE = 0 ; nonblck = 0 ; LOAD = 12'b000000000000;
        #1 reset = 1 ; ENABLE = 0 ; nonblck = 0 ; LOAD = 12'b000000000000 ;  // Reset
        #1 reset = 0 ; ENABLE = 0 ; nonblck = 0 ; LOAD = 12'b000000000000 ;  // Nada
        #1 reset = 0 ; ENABLE = 1 ; nonblck = 0 ; LOAD = 12'b000000000000 ;  // ENABLE = 1 --> Contando
        #1 reset = 0 ; ENABLE = 1 ; nonblck = 0 ; LOAD = 12'b000000000000 ;  // ENABLE = 1 --> Contando
        #1 reset = 0 ; ENABLE = 1 ; nonblck = 0 ; LOAD = 12'b000000000000 ;  // ENABLE = 1 --> Contando
        #1 reset = 0 ; ENABLE = 0 ; nonblck = 0 ; LOAD = 12'b000000000000 ;  // Nada
        #1 reset = 0 ; ENABLE = 0 ; nonblck = 1 ; LOAD = 12'b000000100000 ;  // nonblck = 1 --> LOAD = on -->  Contando desde 32
        #1 reset = 0 ; ENABLE = 1 ; nonblck = 0 ; LOAD = 12'b000000000000 ;  // ENABLE = 1 --> Contando 
        #1 reset = 0 ; ENABLE = 1 ; nonblck = 0 ; LOAD = 12'b000000000000 ;  // ENABLE = 1 --> Contando
        #1 reset = 0 ; ENABLE = 1 ; nonblck = 0 ; LOAD = 12'b000000000000 ;  // ENABLE = 1 --> Contando
        #1 reset = 0 ; ENABLE = 1 ; nonblck = 0 ; LOAD = 12'b000000000000 ;  // ENABLE = 1 --> Contando
        #1 reset = 0 ; ENABLE = 0 ; nonblck = 1 ; LOAD = 12'b000100000000 ;  // nonblck = 1 --> LOAD = on -->  Contando desde 256
        #1 reset = 0 ; ENABLE = 1 ; nonblck = 0 ; LOAD = 12'b000000000000 ;  // ENABLE = 1 --> Contando
        #1 reset = 0 ; ENABLE = 1 ; nonblck = 0 ; LOAD = 12'b000000000000 ;  // ENABLE = 1 --> Contando
        #1 reset = 0 ; ENABLE = 1 ; nonblck = 0 ; LOAD = 12'b000000000000 ;  // ENABLE = 1 --> Contando
        #1 reset = 1 ; ENABLE = 0 ; nonblck = 0 ; LOAD = 12'b000000000000 ;  // Reset
        #1 reset = 0 ; ENABLE = 1 ; nonblck = 0 ; LOAD = 12'b000000000000 ;  // ENABLE = 1 --> Contando
        #1 reset = 0 ; ENABLE = 1 ; nonblck = 0 ; LOAD = 12'b000000000000 ;  // ENABLE = 1 --> Contando
        
    end

    initial
    #20  $finish;

initial 
    begin
       $dumpfile("counter_tb.vcd");
       $dumpvars(0,testbench); 
    end

endmodule

Lab8_Digital1/Ejercicio1-Counter/counter_tb.vcd
$date
	Sat Oct 24 23:23:34 2020
$end
$version
	Icarus Verilog
$end
$timescale
	1ps
$end
$scope module testbench $end
$var wire 12 ! Q [11:0] $end
$var reg 1 " ENABLE $end
$var reg 12 # LOAD [11:0] $end
$var reg 1 $ clk $end
$var reg 1 % nonblck $end
$var reg 1 & reset $end
$scope module CONT $end
$var wire 1 " ENABLE $end
$var wire 12 ' LOAD [11:0] $end
$var wire 1 $ clk $end
$var wire 1 % nonblck $end
$var wire 1 & reset $end
$var reg 12 ( Q [11:0] $end
$upscope $end
$upscope $end
$enddefinitions $end
#0
$dumpvars
bx (
bx '
x&
x%
1$
bx #
x"
bx !
$end
#1
b0 #
b0 '
0%
0"
0&
0$
#2
b0 !
b0 (
1&
1$
#3
0&
0$
#4
b1 !
b1 (
1"
1$
#5
0$
#6
b10 !
b10 (
1$
#7
0"
0$
#8
b100000 !
b100000 (
b100000 #
b100000 '
1%
1$
#9
b0 #
b0 '
0%
1"
0$
#10
b100001 !
b100001 (
1$
#11
0$
#12
b100010 !
b100010 (
1$
#13
b100000000 !
b100000000 (
b100000000 #
b100000000 '
1%
0"
0$
#14
b100000001 !
b100000001 (
b0 #
b0 '
0%
1"
1$
#15
0$
#16
b100000010 !
b100000010 (
1$
#17
b0 !
b0 (
0"
1&
0$
#18
b1 !
b1 (
1"
0&
1$
#19
0$
#20
b10 !
b10 (
1$
