Lab3_Digital1/Circuito2_SOP/Tabla2_SOP.v

// Luis Pedro Molina Velasquez
// Carnet 18822 - Seccion 12

// Tabla 2 - SOP

module gates ();    
    //wire n0 a n2 para not
    //wire a3 a a5 para and
    //wire F out final
    wire n0;
    wire n1; 
    wire n2;
    wire a3;
    wire a4;
    wire a5;
    wire F;

    reg inA,inB,inC;

    not z1 (n0,inA); // -A
    not z2 (n1,inB); // -B
    not z3 (n2,inC); // -C

    and k1 (a3,n0,n1,inC);      
    and k2 (a4,inA,inB,n2);
    and k3 (a5,inA,inB,inC);
   
    or x1 (F,a3,a4,a5);

initial begin
    $display("A B C | Y");
    $display("------| -");
    $monitor("%b %b %b | %b", inA, inB, inC, F);

    //Condicion inicial
    inA = 0;
    inB = 0;
    inC = 0;
    //Combinacion de simulaciones
    #1 inC = 1;
    #1 inB = 1; inC = 0;
    #1 inC = 1;
    #1 inA = 1; inB = 0; inC = 0;
    #1 inC = 1;
    #1 inB = 1; inC = 0;
    #1 inC = 1;
    #1 $finish;             //Finaliza la simulacion

end
initial 
    begin
        $dumpfile("Tabla2_SOP_tb.vcd");
        $dumpvars(0,gates);
    end
endmodule                   //Fin del modulo

Lab3_Digital1/Circuito1_POS/Tabla1_POS_tb.vcd
$date
	Thu Oct 29 14:06:46 2020
$end
$version
	Icarus Verilog
$end
$timescale
	1ps
$end
$scope module gates $end
$var wire 1 ! F $end
$var wire 1 " a3 $end
$var wire 1 # a4 $end
$var wire 1 $ a5 $end
$var wire 1 % n0 $end
$var wire 1 & n1 $end
$var wire 1 ' n2 $end
$var reg 1 ( inA $end
$var reg 1 ) inB $end
$var reg 1 * inC $end
$upscope $end
$enddefinitions $end
#0
$dumpvars
0*
0)
0(
1'
1&
1%
1$
1#
1"
1!
$end
#1
0!
0"
0'
1*
#2
1!
1'
1"
0&
0*
1)
#3
0!
0#
0'
1*
#4
1!
1'
1&
1#
0%
0*
0)
1(
#5
0'
1*
#6
0!
0$
1'
0&
0*
1)
#7
1!
1$
0'
1*
