Lab5_Digital1/muxes.v
// Luis Pedro Molina Velásquez - Carné 18822 
// Electrónica Digital 1 - Sección 12
// Laboratorio 5

// Construcción de los Mux:
// Mux 2:1

module mux2a1(output wire F, input wire D0, D1, S);

    // Declaración de cables
    assign F = S ? D1 : D0;

endmodule

// Mux 4:1

module mux4a1(output wire F, input wire D1, D2, D3, D4, S1, S2);

    // Declaración de cables entre muxes
    wire ca1, ca2;
    // Implementación de módulos
    mux2a1 connect1(ca1, D1, D2, S1);
    mux2a1 connect2(ca2, D3, D4, S1);
    mux2a1 connect3(F, ca1, ca2, S2);

endmodule

// Mux 8:1

module mux8a1(output wire F, input wire D1, D2, D3, D4, D5, D6, D7, D8, S1, S2, S3);

    // Declaraciónn de cables entre muxes
    wire ca1, ca2, ca3, ca4;
    // Implementación de módulos
    mux2a1 connect1(ca1, D1, D2, S1);
    mux2a1 connect2(ca2, D3, D4, S1);
    mux2a1 connect3(ca3, D5, D6, S1);
    mux2a1 connect4(ca4, D7, D8, S1);
    mux4a1 connect5(F, ca1, ca2, ca3, ca4, S2, S3);

endmodule

// Conección de cables a muxes

// Tabla 1
// Tabla 1 - mux 8:1

module t1mux8a1(output wire F, input wire inA, inB, inC);

    // Declaración de cables
    wire high, low;
    // Asignación de valores a mis cables
    assign high = 1;
    assign low = 0;
    // Construcción del mux 8:1
    mux8a1 connect(F, low, high, high, low, high, low, low, high, inA, inB, inC);

endmodule

// Tabla 1 - mux 4:1

module t1mux4a1(output wire F, input wire inA, inB, inC);

    // Declaración de cables
    wire R1;
    // Asignación de compuertas
    assign R1 = ~inC;
    // Construcción del mux 4:1 
    mux4a1 connect(F, inC, R1, R1, inC, inA, inB);

endmodule

// Tabla 1 - mux 2:1

module t1mux2a1(output wire F, input wire inA, inB, inC);

    // Declaración de cables
    wire L, P;
    // Asignación de compuertas
    assign L = inB ^ inC;
    assign P = inB ~^inC;
    // Construcción del mux 2:1
    mux2a1 connect(F, L, P, inA);

endmodule

// Tabla 2
// Tabla 2 - mux 8:1

module t2mux8a1(output wire F, input wire inA, inB, inC);
    
    // Declaración de cables
    wire high, low;
    // Asignación de valores a mis cables
    assign high = 1;
    assign low = 0;
    // Construcción del mux 8:1
    mux8a1 connect(F, high, low, low, low, low, high, high, low, inC, inB, inA);

endmodule

// Tabla 2 - mux 4:1

module t2mux4a1(output wire F, input wire inA, inB, inC);

    // Declaración de cables
    wire H, L, R1;
    // Declaración de compuertas
    assign H = 1;
    assign L = 0;
    assign R1 = ~inC;
    // Consntrucción del mux 4:1
    mux4a1 connect(F, R1, L, inC, R1, inB, inA);

endmodule

// Tabla 2 - mux 2:1

module t2mux2a1(output wire F, input wire inA, inB, inC);

    // Declaración de cables
    wire L, P; 
    // Declaración de compuertas
    assign L = (inB) ~| (inC);
    assign P = (inB) ^ (inC);
    // Construcción del mux 2:1
    mux2a1 connect(F, L, P, inA);

endmodule

Lab5_Digital1/muxes_tb.v
// Luis Pedro Molina Velásquez - Carné 18822 
// Electrónica Digital 1 - Sección 12
// Laboratorio 5

// Testbench 

module testbench;

    // Definición de variables para Tabla 1, Tabla 2 y Salidas

    reg T1A1, T1B1, T1C1, T1A2, T1B2, T1C2, T1A3, T1B3, T1C3;
    reg T2A1, T2B1, T2C1, T2A2, T2B2, T2C2, T2A3, T2B3, T2C3;
    wire F1, F2, F3, F4, F5, F6;

    // Construcción de modulos

    // Módulos para Tabla 1 - Mux 8:1, Mux 4:1 y Mux 2:1
    t1mux8a1 m1(F1, T1A1, T1B1, T1C1);
    t1mux4a1 m2(F2, T1A2, T1B2, T1C2);
    t1mux2a1 m3(F3, T1A3, T1B3, T1C3);

    // Módulos para Tabla 2 - Mux 8:1, Mux 4:1 y Mux 2:1
    t2mux8a1 m4(F4, T2A1, T2B1, T2C1);
    t2mux4a1 m5(F5, T2A2, T2B2, T2C2);
    t2mux2a1 m6(F6, T2A3, T2B3, T2C3);

// Tabla 1 - mux 8:1

        initial begin
            $display("Tabla 1 - Mux 8:1");
            $display(" A B C | Y");
            $display("------| -");
            $monitor("%b %b %b | %b", T1A1, T1B1, T1C1, F1);
            T1A1 = 0 ; T1B1 = 0 ; T1C1 = 0 ;
            #1 T1A1 = 0 ; T1B1 = 0 ; T1C1 = 1 ;
            #1 T1A1 = 0 ; T1B1 = 1 ; T1C1 = 0 ;
            #1 T1A1 = 0 ; T1B1 = 1 ; T1C1 = 1 ;
            #1 T1A1 = 1 ; T1B1 = 0 ; T1C1 = 0 ;
            #1 T1A1 = 1 ; T1B1 = 0 ; T1C1 = 1 ;
            #1 T1A1 = 1 ; T1B1 = 1 ; T1C1 = 0 ;
            #1 T1A1 = 1 ; T1B1 = 1 ; T1C1 = 1 ;
        end

// Tabla 1 - mux 4:1

        initial begin
            #8
            $display("\n\n");
            $display("Tabla 1 - Mux 4:1");
            $display(" A B C | Y");
            $display("------| -");
            $monitor("%b %b %b | %b", T1A2, T1B2, T1C2, F2);
            T1A2 = 0 ; T1B2 = 0 ; T1C2 = 0 ;
            #1 T1A2 = 0 ; T1B2 = 0 ; T1C2 = 1 ;
            #1 T1A2 = 0 ; T1B2 = 1 ; T1C2 = 0 ;
            #1 T1A2 = 0 ; T1B2 = 1 ; T1C2 = 1 ;
            #1 T1A2 = 1 ; T1B2 = 0 ; T1C2 = 0 ;
            #1 T1A2 = 1 ; T1B2 = 0 ; T1C2 = 1 ;
            #1 T1A2 = 1 ; T1B2 = 1 ; T1C2 = 0 ;
            #1 T1A2 = 1 ; T1B2 = 1 ; T1C2 = 1 ;          
        end

// Tabla 1 - mux 2:1

        initial begin
            #16 
            $display("\n\n");
            $display("Tabla 1 - Mux 2:1");
            $display(" A B C | Y");
            $display("------| -");
            $monitor("%b %b %b | %b", T1A3, T1B3, T1C3, F3);
            T1A3 = 0 ; T1B3 = 0 ; T1C3 = 0 ;
            #1 T1A3 = 0 ; T1B3 = 0 ; T1C3 = 1 ;
            #1 T1A3 = 0 ; T1B3 = 1 ; T1C3 = 0 ;
            #1 T1A3 = 0 ; T1B3 = 1 ; T1C3 = 1 ;
            #1 T1A3 = 1 ; T1B3 = 0 ; T1C3 = 0 ;
            #1 T1A3 = 1 ; T1B3 = 0 ; T1C3 = 1 ;
            #1 T1A3 = 1 ; T1B3 = 1 ; T1C3 = 0 ;
            #1 T1A3 = 1 ; T1B3 = 1 ; T1C3 = 1 ;
        end

// Tabla 2 - mux 8:1

        initial begin
            #24
            $display("\n\n");
            $display("Tabla 2 - Mux 8:1");
            $display(" A B C | Y");
            $display("------| -");
            $monitor("%b %b %b | %b", T2A1, T2B1, T2C1, F4);
            T2A1 = 0 ; T2B1 = 0 ; T2C1 = 0 ;
            #1 T2A1 = 0 ; T2B1 = 0 ; T2C1 = 1 ;
            #1 T2A1 = 0 ; T2B1 = 1 ; T2C1 = 0 ;
            #1 T2A1 = 0 ; T2B1 = 1 ; T2C1 = 1 ;
            #1 T2A1 = 1 ; T2B1 = 0 ; T2C1 = 0 ;
            #1 T2A1 = 1 ; T2B1 = 0 ; T2C1 = 1 ;
            #1 T2A1 = 1 ; T2B1 = 1 ; T2C1 = 0 ;
            #1 T2A1 = 1 ; T2B1 = 1 ; T2C1 = 1 ;
        end

// Tabla 2 - mux 4:1 

        initial begin
            #32
            $display("\n\n");
            $display("Tabla 2 - Mux 4:1");
            $display(" A B C | Y");
            $display("------| -");
            $monitor("%b %b %b | %b", T2A2, T2B2, T2C2, F5);
            T2A2 = 0 ; T2B2 = 0 ; T2C2 = 0 ;
            #1 T2A2 = 0 ; T2B2 = 0 ; T2C2 = 1 ;
            #1 T2A2 = 0 ; T2B2 = 1 ; T2C2 = 0 ;
            #1 T2A2 = 0 ; T2B2 = 1 ; T2C2 = 1 ;
            #1 T2A2 = 1 ; T2B2 = 0 ; T2C2 = 0 ;
            #1 T2A2 = 1 ; T2B2 = 0 ; T2C2 = 1 ;
            #1 T2A2 = 1 ; T2B2 = 1 ; T2C2 = 0 ;
            #1 T2A2 = 1 ; T2B2 = 1 ; T2C2 = 1 ;
        end

// Tabla 2 - mux 2:1

        initial begin
            #40
            $display("\n\n");
            $display("Tabla 2 - Mux 2:1");
            $display(" A B C | Y");
            $display("------| -");
            $monitor("%b %b %b | %b", T2A3, T2B3, T2C3, F6);
            T2A3 = 0 ; T2B3 = 0 ; T2C3 = 0 ;
            #1 T2A3 = 0 ; T2B3 = 0 ; T2C3 = 1 ;
            #1 T2A3 = 0 ; T2B3 = 1 ; T2C3 = 0 ;
            #1 T2A3 = 0 ; T2B3 = 1 ; T2C3 = 1 ;
            #1 T2A3 = 1 ; T2B3 = 0 ; T2C3 = 0 ;
            #1 T2A3 = 1 ; T2B3 = 0 ; T2C3 = 1 ;
            #1 T2A3 = 1 ; T2B3 = 1 ; T2C3 = 0 ;
            #1 T2A3 = 1 ; T2B3 = 1 ; T2C3 = 1 ;
        end

        initial 
        #51 $finish;

initial
    begin
        $dumpfile("muxes_tb.vcd");
        $dumpvars(0, testbench);
    end

endmodule           // Fin del módulo

Lab5_Digital1/muxes_tb.vcd
$date
	Sat Sep 12 12:46:51 2020
$end
$version
	Icarus Verilog
$end
$timescale
	1ps
$end
$scope module testbench $end
$var wire 1 ! F6 $end
$var wire 1 " F5 $end
$var wire 1 # F4 $end
$var wire 1 $ F3 $end
$var wire 1 % F2 $end
$var wire 1 & F1 $end
$var reg 1 ' T1A1 $end
$var reg 1 ( T1A2 $end
$var reg 1 ) T1A3 $end
$var reg 1 * T1B1 $end
$var reg 1 + T1B2 $end
$var reg 1 , T1B3 $end
$var reg 1 - T1C1 $end
$var reg 1 . T1C2 $end
$var reg 1 / T1C3 $end
$var reg 1 0 T2A1 $end
$var reg 1 1 T2A2 $end
$var reg 1 2 T2A3 $end
$var reg 1 3 T2B1 $end
$var reg 1 4 T2B2 $end
$var reg 1 5 T2B3 $end
$var reg 1 6 T2C1 $end
$var reg 1 7 T2C2 $end
$var reg 1 8 T2C3 $end
$scope module m1 $end
$var wire 1 9 high $end
$var wire 1 ' inA $end
$var wire 1 * inB $end
$var wire 1 - inC $end
$var wire 1 : low $end
$var wire 1 & F $end
$scope module connect $end
$var wire 1 : D1 $end
$var wire 1 9 D2 $end
$var wire 1 9 D3 $end
$var wire 1 : D4 $end
$var wire 1 9 D5 $end
$var wire 1 : D6 $end
$var wire 1 : D7 $end
$var wire 1 9 D8 $end
$var wire 1 ' S1 $end
$var wire 1 * S2 $end
$var wire 1 - S3 $end
$var wire 1 ; ca4 $end
$var wire 1 < ca3 $end
$var wire 1 = ca2 $end
$var wire 1 > ca1 $end
$var wire 1 & F $end
$scope module connect1 $end
$var wire 1 : D0 $end
$var wire 1 9 D1 $end
$var wire 1 ' S $end
$var wire 1 > F $end
$upscope $end
$scope module connect2 $end
$var wire 1 9 D0 $end
$var wire 1 : D1 $end
$var wire 1 ' S $end
$var wire 1 = F $end
$upscope $end
$scope module connect3 $end
$var wire 1 9 D0 $end
$var wire 1 : D1 $end
$var wire 1 ' S $end
$var wire 1 < F $end
$upscope $end
$scope module connect4 $end
$var wire 1 : D0 $end
$var wire 1 9 D1 $end
$var wire 1 ' S $end
$var wire 1 ; F $end
$upscope $end
$scope module connect5 $end
$var wire 1 > D1 $end
$var wire 1 = D2 $end
$var wire 1 < D3 $end
$var wire 1 ; D4 $end
$var wire 1 * S1 $end
$var wire 1 - S2 $end
$var wire 1 ? ca2 $end
$var wire 1 @ ca1 $end
$var wire 1 & F $end
$scope module connect1 $end
$var wire 1 > D0 $end
$var wire 1 = D1 $end
$var wire 1 * S $end
$var wire 1 @ F $end
$upscope $end
$scope module connect2 $end
$var wire 1 < D0 $end
$var wire 1 ; D1 $end
$var wire 1 * S $end
$var wire 1 ? F $end
$upscope $end
$scope module connect3 $end
$var wire 1 @ D0 $end
$var wire 1 ? D1 $end
$var wire 1 - S $end
$var wire 1 & F $end
$upscope $end
$upscope $end
$upscope $end
$upscope $end
$scope module m2 $end
$var wire 1 A R1 $end
$var wire 1 ( inA $end
$var wire 1 + inB $end
$var wire 1 . inC $end
$var wire 1 % F $end
$scope module connect $end
$var wire 1 . D1 $end
$var wire 1 A D2 $end
$var wire 1 A D3 $end
$var wire 1 . D4 $end
$var wire 1 ( S1 $end
$var wire 1 + S2 $end
$var wire 1 B ca2 $end
$var wire 1 C ca1 $end
$var wire 1 % F $end
$scope module connect1 $end
$var wire 1 . D0 $end
$var wire 1 A D1 $end
$var wire 1 ( S $end
$var wire 1 C F $end
$upscope $end
$scope module connect2 $end
$var wire 1 A D0 $end
$var wire 1 . D1 $end
$var wire 1 ( S $end
$var wire 1 B F $end
$upscope $end
$scope module connect3 $end
$var wire 1 C D0 $end
$var wire 1 B D1 $end
$var wire 1 + S $end
$var wire 1 % F $end
$upscope $end
$upscope $end
$upscope $end
$scope module m3 $end
$var wire 1 D L $end
$var wire 1 E P $end
$var wire 1 ) inA $end
$var wire 1 , inB $end
$var wire 1 / inC $end
$var wire 1 $ F $end
$scope module connect $end
$var wire 1 D D0 $end
$var wire 1 E D1 $end
$var wire 1 ) S $end
$var wire 1 $ F $end
$upscope $end
$upscope $end
$scope module m4 $end
$var wire 1 F high $end
$var wire 1 0 inA $end
$var wire 1 3 inB $end
$var wire 1 6 inC $end
$var wire 1 G low $end
$var wire 1 # F $end
$scope module connect $end
$var wire 1 F D1 $end
$var wire 1 G D2 $end
$var wire 1 G D3 $end
$var wire 1 G D4 $end
$var wire 1 G D5 $end
$var wire 1 F D6 $end
$var wire 1 F D7 $end
$var wire 1 G D8 $end
$var wire 1 6 S1 $end
$var wire 1 3 S2 $end
$var wire 1 0 S3 $end
$var wire 1 H ca4 $end
$var wire 1 I ca3 $end
$var wire 1 J ca2 $end
$var wire 1 K ca1 $end
$var wire 1 # F $end
$scope module connect1 $end
$var wire 1 F D0 $end
$var wire 1 G D1 $end
$var wire 1 6 S $end
$var wire 1 K F $end
$upscope $end
$scope module connect2 $end
$var wire 1 G D0 $end
$var wire 1 G D1 $end
$var wire 1 6 S $end
$var wire 1 J F $end
$upscope $end
$scope module connect3 $end
$var wire 1 G D0 $end
$var wire 1 F D1 $end
$var wire 1 6 S $end
$var wire 1 I F $end
$upscope $end
$scope module connect4 $end
$var wire 1 F D0 $end
$var wire 1 G D1 $end
$var wire 1 6 S $end
$var wire 1 H F $end
$upscope $end
$scope module connect5 $end
$var wire 1 K D1 $end
$var wire 1 J D2 $end
$var wire 1 I D3 $end
$var wire 1 H D4 $end
$var wire 1 3 S1 $end
$var wire 1 0 S2 $end
$var wire 1 L ca2 $end
$var wire 1 M ca1 $end
$var wire 1 # F $end
$scope module connect1 $end
$var wire 1 K D0 $end
$var wire 1 J D1 $end
$var wire 1 3 S $end
$var wire 1 M F $end
$upscope $end
$scope module connect2 $end
$var wire 1 I D0 $end
$var wire 1 H D1 $end
$var wire 1 3 S $end
$var wire 1 L F $end
$upscope $end
$scope module connect3 $end
$var wire 1 M D0 $end
$var wire 1 L D1 $end
$var wire 1 0 S $end
$var wire 1 # F $end
$upscope $end
$upscope $end
$upscope $end
$upscope $end
$scope module m5 $end
$var wire 1 N H $end
$var wire 1 O L $end
$var wire 1 P R1 $end
$var wire 1 1 inA $end
$var wire 1 4 inB $end
$var wire 1 7 inC $end
$var wire 1 " F $end
$scope module connect $end
$var wire 1 P D1 $end
$var wire 1 O D2 $end
$var wire 1 7 D3 $end
$var wire 1 P D4 $end
$var wire 1 4 S1 $end
$var wire 1 1 S2 $end
$var wire 1 Q ca2 $end
$var wire 1 R ca1 $end
$var wire 1 " F $end
$scope module connect1 $end
$var wire 1 P D0 $end
$var wire 1 O D1 $end
$var wire 1 4 S $end
$var wire 1 R F $end
$upscope $end
$scope module connect2 $end
$var wire 1 7 D0 $end
$var wire 1 P D1 $end
$var wire 1 4 S $end
$var wire 1 Q F $end
$upscope $end
$scope module connect3 $end
$var wire 1 R D0 $end
$var wire 1 Q D1 $end
$var wire 1 1 S $end
$var wire 1 " F $end
$upscope $end
$upscope $end
$upscope $end
$scope module m6 $end
$var wire 1 S L $end
$var wire 1 T P $end
$var wire 1 2 inA $end
$var wire 1 5 inB $end
$var wire 1 8 inC $end
$var wire 1 ! F $end
$scope module connect $end
$var wire 1 S D0 $end
$var wire 1 T D1 $end
$var wire 1 2 S $end
$var wire 1 ! F $end
$upscope $end
$upscope $end
$upscope $end
$enddefinitions $end
#0
$dumpvars
xT
xS
xR
xQ
xP
0O
1N
xM
xL
xK
0J
xI
xH
0G
1F
xE
xD
xC
xB
xA
0@
1?
0>
1=
1<
0;
0:
19
x8
x7
x6
x5
x4
x3
x2
x1
x0
x/
x.
0-
x,
x+
0*
x)
x(
0'
0&
x%
x$
x#
x"
x!
$end
#1
1&
1-
#2
1@
0?
0-
1*
#3
0&
1-
#4
1&
1>
0=
0<
1;
0-
0*
1'
#5
0&
1-
#6
0@
1?
0-
1*
#7
1&
1-
#8
1B
1A
0%
0C
0.
0+
0(
#9
0B
1%
0A
1C
1.
#10
1B
1A
0C
1%
0.
1+
#11
0%
0B
0A
1C
1.
#12
1%
1A
1C
0.
0+
1(
#13
0%
0C
0A
1B
1.
#14
1C
1A
0B
0%
0.
1+
#15
0C
1%
0A
1B
1.
#16
0$
0D
1E
0/
0,
0)
#17
1$
1D
0E
1/
#18
0/
1,
#19
0$
0D
1E
1/
#20
1$
0/
0,
1)
#21
0$
1D
0E
1/
#22
0/
1,
#23
1$
0D
1E
1/
#24
1#
1M
0L
1K
0I
1H
06
03
00
#25
0#
0M
1L
0K
1I
0H
16
#26
1K
0I
1H
1L
06
13
#27
0L
0K
1I
0H
16
#28
1M
0#
1K
0I
1H
0L
06
03
10
#29
1#
0M
1L
0K
1I
0H
16
#30
1#
1K
0I
1H
1L
06
13
#31
0#
0L
0K
1I
0H
16
#32
1"
1R
1P
0Q
07
04
01
#33
0"
0R
0P
1Q
17
#34
1P
1Q
07
14
#35
0Q
0P
17
#36
1R
1P
07
04
11
#37
0R
1"
0P
1Q
17
#38
1"
1P
1Q
07
14
#39
0"
0Q
0P
17
#40
1!
1S
0T
08
05
02
#41
0!
0S
1T
18
#42
08
15
#43
0T
18
#44
1S
08
05
12
#45
1!
0S
1T
18
#46
08
15
#47
0!
0T
18
