Lab6_Digital1/Ejercicio_6/Ejercicio_1/Ejercicio_1.v
// Luis Pedro Molina Velásquez - 18822
// Electrónica Digital 1 - Sección 12
// Laboratorio 6 - Ejercicio 6 - Módulo para FSM Mealy de ejercicio 1

// Módulo de Flip Flop tipo D de 1 bit

module FFD(input clk, reset, D, output reg Q);

    always @ (posedge clk or posedge reset)begin
        if(reset)
            Q <= 1'b0;
        else
            Q <= D;
    end
endmodule

module FFD2(input clk, reset, input [1:0]D, output reg [1:0]Q);
                                                                                           
    always @ (posedge clk or posedge reset)begin
        if(reset)
            Q <= 2'b00;
        else
            Q[1] <= D[1];
            Q[0] <= D[0];
    end 
endmodule

module Ejercicio1(input A, B, clk, reset, output wire Y, output wire [1:0] S, output wire [1:0]SF);

// Declaración de cables/estados
    wire S0, S1, S0F, S1F;

// Nube combinacional de estados futuros (S0F, S1F)
    assign S0F = (~S1 & ~S0 & A);
    assign S1F = (S0 & B) | (S1 & A & B);
// Nube combinacional de salidas (FSM Mealy)
    assign Y = (S1 & A & B);

// Conexión de Flip Flops tipo D
   FFD T1(.clk(clk), .reset(reset), .D(S1F), .Q(S1));
   FFD T2(clk, reset, S0F, S0);

// Visualización de estados actuales y futuros
    assign S = {S1, S0};
    assign SF = {S1F, S0F};

endmodule

Lab6_Digital1/Ejercicio_6/Ejercicio_1/Ejercicio_1_tb.v
// Luis Pedro Molina Velásquez - 18822
// Electrónica Digital 1 - Sección 12
// Laboratorio 6 - Ejercicio 6 - Módulo testbench para FSM Mealy de ejercicio1

// Módulo testbench - FSM Mealy de ejercicio 1

module testbench();

    reg clk, reset, A, B;
    wire Y;
    wire [1:0] SF, S;

    Ejercicio1 R1(A, B, clk, reset, Y, S, SF);

    initial begin
        $display("clk  reset  A  B  SF  S  | Y");
        $monitor(" %b   %b   %b %b  %b  %b | %b", clk, reset, A, B, SF, S, Y);
    end

    initial begin
        clk = 0 ;
        reset = 0 ;
        A = 0 ; 
        B = 0 ;
        #1 reset = 1;
        #1 reset = 0;
        #5
        A = 1 ; 
        B = 0;
        #10 
        A = 1 ; 
        B = 1 ;
        #15
        A = 1 ;
        B = 1 ;
        #20
        A = 0 ;
        B = 1 ;
        #25
        A = 1 ;
        B = 1 ;
        #30
        A = 1 ;
        B = 0 ;
        #35
        A = 1 ;
        B = 0 ;
        #40 
        A = 0 ;
        B = 1 ;
        #50 $finish; 
    end 
    
    always
    #5 clk = ~clk ;
    
initial 
    begin
        $dumpfile("Ejercicio_1_tb.vcd");
        $dumpvars(0, testbench);
    end

endmodule

Lab6_Digital1/Ejercicio_6/Ejercicio_1/Ejercicio_1_tb.vcd
$date
	Sat Sep 05 21:49:32 2020
$end
$version
	Icarus Verilog
$end
$timescale
	1ps
$end
$scope module testbench $end
$var wire 1 ! Y $end
$var wire 2 " SF [1:0] $end
$var wire 2 # S [1:0] $end
$var reg 1 $ A $end
$var reg 1 % B $end
$var reg 1 & clk $end
$var reg 1 ' reset $end
$scope module R1 $end
$var wire 1 $ A $end
$var wire 1 % B $end
$var wire 1 ( S0F $end
$var wire 1 ) S1F $end
$var wire 1 ! Y $end
$var wire 1 & clk $end
$var wire 1 ' reset $end
$var wire 2 * SF [1:0] $end
$var wire 1 + S1 $end
$var wire 1 , S0 $end
$var wire 2 - S [1:0] $end
$scope module T1 $end
$var wire 1 ) D $end
$var wire 1 & clk $end
$var wire 1 ' reset $end
$var reg 1 + Q $end
$upscope $end
$scope module T2 $end
$var wire 1 ( D $end
$var wire 1 & clk $end
$var wire 1 ' reset $end
$var reg 1 , Q $end
$upscope $end
$upscope $end
$upscope $end
$enddefinitions $end
#0
$dumpvars
bx -
x,
x+
b0 *
0)
0(
0'
0&
0%
0$
bx #
b0 "
0!
$end
#1
0+
b0 #
b0 -
0,
1'
#2
0'
#5
1&
#7
b1 "
b1 *
1(
1$
#10
0&
#15
b0 "
b0 *
0(
b1 #
b1 -
1,
1&
#17
b10 "
b10 *
1)
1%
#20
0&
#25
1!
0,
b10 #
b10 -
1+
1&
#30
0&
#35
1&
#40
0&
#45
1&
#50
0&
#52
b0 "
b0 *
0)
0!
0$
#55
b0 #
b0 -
0+
1&
#60
0&
#65
1&
#70
0&
#75
1&
#77
b1 "
b1 *
1(
1$
#80
0&
#85
0(
b10 "
b10 *
1)
b1 #
b1 -
1,
1&
#90
0&
#95
1!
b10 "
b10 *
1)
1+
b10 #
b10 -
0,
1&
#100
0&
#105
1&
#107
b0 "
b0 *
0)
0!
0%
#110
0&
#115
b1 "
b1 *
1(
b0 #
b0 -
0+
1&
#120
0&
#125
b0 "
b0 *
0(
b1 #
b1 -
1,
1&
#130
0&
#135
b1 "
b1 *
1(
b0 #
b0 -
0,
1&
#140
0&
#145
b0 "
b0 *
0(
b1 #
b1 -
1,
1&
#150
0&
#155
b1 "
b1 *
1(
b0 #
b0 -
0,
1&
#160
0&
#165
b0 "
b0 *
0(
b1 #
b1 -
1,
1&
#170
0&
#175
b1 "
b1 *
1(
b0 #
b0 -
0,
1&
#180
0&
#182
b0 "
b0 *
0(
1%
0$
