Lab3_Digital1/Circuito2_POS/Tabla2_POS.v

// Luis Pedro Molina Velasquez
// Carne 18822 - Seccion 12

// Tabla 2 - POS

module gates ();
    //wire n0 al n2 definidos para not   
    //wire a3 al a5 definidos para or
    //wire F para salida final
    wire n0;
    wire n1;
    wire n2;
    wire a3;
    wire a4;
    wire a5;
    wire a6;
    wire a7;
    wire F;

    reg inA,inB,inC; 

    not z1 (n0,inA);  //-A
    not z2 (n1,inB);  //-B
    not z3 (n2,inC);  //-C

    or x1 (a3,inA,inB,inC);
    or x2 (a4,inA,n1,inC);
    or x3 (a5,inA,n1,n2);
    or x4 (a6,n0,inB,inC);
    or x5 (a7,n0,inB,n2);

    and k1 (F,a3,a4,a5,a6,a7);

initial begin
    $display("A B C | Y");
    $display("------| -");
    $monitor ("%b %b %b | %b",inA, inB, inC, F);
    
    //Condicion inicial
    inA = 0;
    inB = 0;
    inC = 0;
    //Combinacion de simulaciones
    #1 inC = 1;
    #1 inB = 1; inC = 0;
    #1 inC = 1;
    #1 inA = 1; inB = 0 ; inC = 0;
    #1 inC = 1;
    #1 inB = 1; inC = 0;
    #1 inC = 1;
    #1 $finish;              // Finaliza la simulacion

end
initial 
    begin
        $dumpfile("Tabla2_POS_tb.vcd");
        $dumpvars(0,gates);
    end
endmodule                   //Fin del modulo

Lab3_Digital1/Circuito2_POS/Tabla2_POS_tb.vcd
$date
	Sat Aug 01 20:51:58 2020
$end
$version
	Icarus Verilog
$end
$timescale
	1ps
$end
$scope module gates $end
$var wire 1 ! F $end
$var wire 1 " a3 $end
$var wire 1 # a4 $end
$var wire 1 $ a5 $end
$var wire 1 % a6 $end
$var wire 1 & a7 $end
$var wire 1 ' n0 $end
$var wire 1 ( n1 $end
$var wire 1 ) n2 $end
$var reg 1 * inA $end
$var reg 1 + inB $end
$var reg 1 , inC $end
$upscope $end
$enddefinitions $end
#0
$dumpvars
0,
0+
0*
1)
1(
1'
1&
1%
1$
1#
0"
0!
$end
#1
1!
1"
0)
1,
#2
0!
0#
1)
0(
0,
1+
#3
0$
1#
0)
1,
#4
1)
1&
0%
1(
1$
0'
0,
0+
1*
#5
0&
1%
0)
1,
#6
1!
1)
1&
0(
0,
1+
#7
0)
1,
