Lab4_Digital1/Ejercicio 4/codigo.v
// Luis Pedro Molina Velásquez - Carné 18822
// Electrónica Digital 1 - Sección 12
// Laboratorio #4 

// Modulos con Gate Level Modelling
// EJERCICIO 1 - TABLAS 1 A 4

// Ejercicio 1 - Tabla 1 - Y = A'C' + AC + AB'

module gates_eje1_tab1 (input wire inA, inB, inC, output wire F);
    // Compuertas not
    wire n1;    // A
    wire n2;    // B
    wire n3;    // C

    // Compuertas and
    wire a1;
    wire a2;
    wire a3;

    // Compuertas lógicas
    not (n1,inA);  // A'
    not (n2,inB);  // B'
    not (n3,inC);  // C'

    and (a1,n1,n3);
    and (a2,inA,inC);
    and (a3,inA,n2);

    or (F,a1,a2,a3);

endmodule

//Ejercicio 1 - Tabla 2 - Y = B'

module gates_eje1_tab2 (input wire inA, inB, inC, output wire F);

    // Compuerta not
    wire n2;    // B

    // Compuertas lógicas
    not (n2,inB);   // B'
    
    or (F,n2);

endmodule

//Ejercicio 1 - Tabla 3 - Y = A'B'C'D' + A'B'CD + A'BC'D + A'BCD' + ABC'D' + ABCD + AB'C'D + AB'CD'

module gates_eje1_tab3 (input wire inA, inB, inC, inD, output wire F);

    // Compuertas not
    wire n1;    // A
    wire n2;    // B
    wire n3;    // C
    wire n4;    // D

    // Compuertas and
    wire a1;
    wire a2;
    wire a3;
    wire a4;
    wire a5;
    wire a6;
    wire a7;
    wire a8;

    // Compuertas lógicas
    not (n1,inA);    // A'
    not (n2,inB);    // B'
    not (n3,inC);    // C'
    not (n4,inD);    // D'

    and (a1,n1,n2,n3,n4);
    and (a2,n1,n2,inC,inD);
    and (a3,n1,inB,n3,inD);
    and (a4,n1,inB,inC,n4);
    and (a5,inA,inB,n3,n4);
    and (a6,inA,inB,inC,inD);
    and (a7,inA,n2,n3,inD);
    and (a8,inA,n2,inC,n4);

    or (F,a1,a2,a3,a4,a5,a6,a7,a8);

endmodule


// Ejercicio 1 - Tabla 4 - Y = A'B'D' + A'C'D + BD + AC'D' + AC

module gates_eje1_tab4 (input wire inA, inB, inC, inD, output wire F);

    // Compuertas not
    wire n1;    // A
    wire n2;    // B
    wire n3;    // C
    wire n4;    // D

    // Compuertas and
    wire a1;
    wire a2;
    wire a3;
    wire a4;
    wire a5;

    // Compuertas lógicas
    not (n1,inA);    // A'
    not (n2,inB);    // B'
    not (n3,inC);    // C'
    not (n4,inD);    // D'

    and (a1,n1,n2,n4); 
    and (a2,n1,n3,inD);
    and (a3,inB,inD);
    and (a4,inA,n3,n4);
    and (a5,inA,inC);

    or (F,a1,a2,a3,a4,a5);

endmodule

// Módulos con operadores lógicos
// EJERCICIO 2 - ECUACIONES 1 A 4

// Ejercicio 2 - Ecuación 1 - Y = B'C'D' + AC' + ACD' + AB'C

module gates_eje2_ec1 (input wire inA, inB, inC, inD, output wire F);

    assign F = (~inB & ~inC & ~inD) | (inA & ~inC) | (inA & inC & ~inD) | (inA & ~inB & inC);

endmodule

// Ejercicio 2 - Ecuación 2 - Y = B' +AC

module gates_eje2_ec2 (input wire inA, inB, inC, output wire F);

    assign F = (~inB) | (inA & inC);

endmodule

// Ejercicio 2 - Ecuación 3 - Y = B + C'D + AD

module gates_eje2_ec3 (input wire inA, inB, inC, inD, output wire F);

    assign F = (inB) | (~inC & inD) | (inA & inD);

endmodule

// Ejercicio 2 - Ecuación 4 - Y = A'C' + B 

module gates_eje2_ec4 (input wire inA, inB, inC, output wire F);

    assign F =  (~inA & ~inC) | (inB);

endmodule

Lab4_Digital1/Ejercicio 4/codigo_tb.v
// Luis Pedro Molina Velásquez - Carné 18822
// Electrónica Digital 1 - Sección 12
// Laboratorio #4 

// Módulo testbench


module testbench();

// Definición de variables, inputs para cada ecuación:

    reg E1A1, E1B1, E1C1, E1A2, E1B2, E1C2, E1A3, E1B3, E1C3, E1D3, E1A4, E1B4, E1C4, E1D4, 
    E2A1, E2B1, E2C1, E2D1, E2A2, E2B2, E2C2, E2A3, E2B3, E2C3, E2D3, E2A4, E2B4, E2C4;

    wire E1F1, E1F2, E1F3, E1F4, E2F1, E2F2, E2F3, E2F4;

// Asignación de variables a Gate level Modelling - Ejercicio 1 - Tablas 1 a 4

    gates_eje1_tab1 t1(E1A1, E1B1, E1C1, E1F1);
    gates_eje1_tab2 t2(E1A2, E1B2, E1C2, E1F2);
    gates_eje1_tab3 t3(E1A3, E1B3, E1C3, E1D3, E1F3);
    gates_eje1_tab4 t4(E1A4, E1B4, E1C4, E1D4, E1F4);

// Asignación de variables a módulos con Operadores lógicos - Ejercicio 2 - Ecuaciones 1 a 4

    gates_eje2_ec1 e1(E2A1, E2B1, E2C1, E2D1, E2F1);
    gates_eje2_ec2 e2(E2A2, E2B2, E2C2, E2F2);
    gates_eje2_ec3 e3(E2A3, E2B3, E2C3, E2D3, E2F3);
    gates_eje2_ec4 e4(E2A4, E2B4, E2C4, E2F4);

// Ejercicio 1 - Tabla 1

       initial begin
            $display("A B C | Y");
            $display("------|--");
            $monitor("%b %b %b | %b", E1A1, E1B1, E1C1, E1F1);
            E1A1 =  0 ; E1B1 =  0 ; E1C1 =  0 ;
            # 1 E1A1 =  0 ; E1B1 =  0 ; E1C1 =  1 ;
            # 1 E1A1 =  0 ; E1B1 =  1 ; E1C1 =  0 ;
            # 1 E1A1 =  0 ; E1B1 =  1 ; E1C1 =  1 ;
            # 1 E1A1 =  1 ; E1B1 =  0 ; E1C1 =  0 ;
            # 1 E1A1 =  1 ; E1B1 =  0 ; E1C1 =  1 ;
            # 1 E1A1 =  1 ; E1B1 =  1 ; E1C1 =  0 ;
            # 1 E1A1 =  1 ; E1B1 =  1 ; E1C1 =  1 ;
       end

// Ejercico 1 - Tabla 2

        initial begin
            #8
            $display ("\n");
            $display("A B C | Y");
            $display("------|--");
            $monitor("%b %b %b | %b", E1A2, E1B2, E1C2, E1F2);
            E1A2 =  0 ; E1B2 =  0 ; E1C2 =  0 ;
            # 1 E1A2 =  0 ; E1B2 =  0 ; E1C2 =  1 ;
            # 1 E1A2 =  0 ; E1B2 =  1 ; E1C2 =  0 ;
            # 1 E1A2 =  0 ; E1B2 =  1 ; E1C2 =  1 ;
            # 1 E1A2 =  1 ; E1B2 =  0 ; E1C2 =  0 ;
            # 1 E1A2 =  1 ; E1B2 =  0 ; E1C2 =  1 ;
            # 1 E1A2 =  1 ; E1B2 =  1 ; E1C2 =  0 ;
            # 1 E1A2 =  1 ; E1B2 =  1 ; E1C2 =  1 ;
            
        end

// Ejercicio 1 - Tabla 3

        initial begin
            #16
            $display ("\n");
            $display("A B C D | Y");
            $display("--------|--");
            $monitor("%b %b %b %b | %b", E1A3, E1B3, E1C3, E1D3, E1F3);
            E1A3 =  0 ; E1B3 =  0 ; E1C3 =  0 ; E1D3 =  0 ;
            # 1 E1A3 =  0 ; E1B3 =  0 ; E1C3 =  0 ; E1D3 =  1 ; //1
            # 1 E1A3 =  0 ; E1B3 =  0 ; E1C3 =  1 ; E1D3 =  0 ; //2
            # 1 E1A3 =  0 ; E1B3 =  0 ; E1C3 =  1 ; E1D3 =  1 ; //3
            # 1 E1A3 =  0 ; E1B3 =  1 ; E1C3 =  0 ; E1D3 =  0 ; //4 
            # 1 E1A3 =  0 ; E1B3 =  1 ; E1C3 =  0 ; E1D3 =  1 ; //5
            # 1 E1A3 =  0 ; E1B3 =  1 ; E1C3 =  1 ; E1D3 =  0 ; //6
            # 1 E1A3 =  0 ; E1B3 =  1 ; E1C3 =  1 ; E1D3 =  1 ; //7
            # 1 E1A3 =  1 ; E1B3 =  0 ; E1C3 =  0 ; E1D3 =  0 ; //8
            # 1 E1A3 =  1 ; E1B3 =  0 ; E1C3 =  0 ; E1D3 =  1 ; //9
            # 1 E1A3 =  1 ; E1B3 =  0 ; E1C3 =  1 ; E1D3 =  0 ; //10
            # 1 E1A3 =  1 ; E1B3 =  0 ; E1C3 =  1 ; E1D3 =  1 ; //11    
            # 1 E1A3 =  1 ; E1B3 =  1 ; E1C3 =  0 ; E1D3 =  0 ; //12
            # 1 E1A3 =  1 ; E1B3 =  1 ; E1C3 =  0 ; E1D3 =  1 ; //13
            # 1 E1A3 =  1 ; E1B3 =  1 ; E1C3 =  1 ; E1D3 =  0 ; //14
            # 1 E1A3 =  1 ; E1B3 =  1 ; E1C3 =  1 ; E1D3 =  1 ; //15

        end

// Ejercicio 1 - Tabla 4

        initial begin
            #32
            $display ("\n");
            $display("A B C D | Y");
            $display("--------|--");
            $monitor("%b %b %b %b | %b", E1A4, E1B4, E1C4, E1D4, E1F4);
            E1A4 =  0 ; E1B4 =  0 ; E1C4 =  0 ; E1D4 =  0 ;
            # 1 E1A4 =  0 ; E1B4 =  0 ; E1C4 =  0 ; E1D4 =  1 ; //1
            # 1 E1A4 =  0 ; E1B4 =  0 ; E1C4 =  1 ; E1D4 =  0 ; //2
            # 1 E1A4 =  0 ; E1B4 =  0 ; E1C4 =  1 ; E1D4 =  1 ; //3
            # 1 E1A4 =  0 ; E1B4 =  1 ; E1C4 =  0 ; E1D4 =  0 ; //4 
            # 1 E1A4 =  0 ; E1B4 =  1 ; E1C4 =  0 ; E1D4 =  1 ; //5
            # 1 E1A4 =  0 ; E1B4 =  1 ; E1C4 =  1 ; E1D4 =  0 ; //6
            # 1 E1A4 =  0 ; E1B4 =  1 ; E1C4 =  1 ; E1D4 =  1 ; //7
            # 1 E1A4 =  1 ; E1B4 =  0 ; E1C4 =  0 ; E1D4 =  0 ; //8
            # 1 E1A4 =  1 ; E1B4 =  0 ; E1C4 =  0 ; E1D4 =  1 ; //9
            # 1 E1A4 =  1 ; E1B4 =  0 ; E1C4 =  1 ; E1D4 =  0 ; //10
            # 1 E1A4 =  1 ; E1B4 =  0 ; E1C4 =  1 ; E1D4 =  1 ; //11    
            # 1 E1A4 =  1 ; E1B4 =  1 ; E1C4 =  0 ; E1D4 =  0 ; //12
            # 1 E1A4 =  1 ; E1B4 =  1 ; E1C4 =  0 ; E1D4 =  1 ; //13
            # 1 E1A4 =  1 ; E1B4 =  1 ; E1C4 =  1 ; E1D4 =  0 ; //14
            # 1 E1A4 =  1 ; E1B4 =  1 ; E1C4 =  1 ; E1D4 =  1 ; //15

        end

// Ejercicio 2 - Ecuación 1

        initial begin
            #48
            $display ("\n");
            $display("A B C D | Y");
            $display("--------|--");
            $monitor("%b %b %b %b | %b", E2A1, E2B1, E2C1, E2D1, E2F1);
            E2A1 =  0 ; E2B1 =  0 ; E2C1 =  0 ; E2D1 =  0 ;
            # 1 E2A1 =  0 ; E2B1 =  0 ; E2C1 =  0 ; E2D1 =  1 ; //1
            # 1 E2A1 =  0 ; E2B1 =  0 ; E2C1 =  1 ; E2D1 =  0 ; //2
            # 1 E2A1 =  0 ; E2B1 =  0 ; E2C1 =  1 ; E2D1 =  1 ; //3
            # 1 E2A1 =  0 ; E2B1 =  1 ; E2C1 =  0 ; E2D1 =  0 ; //4 
            # 1 E2A1 =  0 ; E2B1 =  1 ; E2C1 =  0 ; E2D1 =  1 ; //5
            # 1 E2A1 =  0 ; E2B1 =  1 ; E2C1 =  1 ; E2D1 =  0 ; //6
            # 1 E2A1 =  0 ; E2B1 =  1 ; E2C1 =  1 ; E2D1 =  1 ; //7
            # 1 E2A1 =  1 ; E2B1 =  0 ; E2C1 =  0 ; E2D1 =  0 ; //8
            # 1 E2A1 =  1 ; E2B1 =  0 ; E2C1 =  0 ; E2D1 =  1 ; //9
            # 1 E2A1 =  1 ; E2B1 =  0 ; E2C1 =  1 ; E2D1 =  0 ; //10
            # 1 E2A1 =  1 ; E2B1 =  0 ; E2C1 =  1 ; E2D1 =  1 ; //11    
            # 1 E2A1 =  1 ; E2B1 =  1 ; E2C1 =  0 ; E2D1 =  0 ; //12
            # 1 E2A1 =  1 ; E2B1 =  1 ; E2C1 =  0 ; E2D1 =  1 ; //13
            # 1 E2A1 =  1 ; E2B1 =  1 ; E2C1 =  1 ; E2D1 =  0 ; //14
            # 1 E2A1 =  1 ; E2B1 =  1 ; E2C1 =  1 ; E2D1 =  1 ; //15      

        end

// Ejercicio 2 - Ecuación 2

        initial begin
            #64
            $display ("\n");
            $display("A B C | Y");
            $display("------|--");
            $monitor("%b %b %b | %b", E2A2, E2B2, E2C2, E2F2);
            E2A2 =  0 ; E2B2 =  0 ; E2C2 =  0 ;
            # 1 E2A2 =  0 ; E2B2 =  0 ; E2C2 =  1 ;
            # 1 E2A2 =  0 ; E2B2 =  1 ; E2C2 =  0 ;
            # 1 E2A2 =  0 ; E2B2 =  1 ; E2C2 =  1 ;
            # 1 E2A2 =  1 ; E2B2 =  0 ; E2C2 =  0 ;
            # 1 E2A2 =  1 ; E2B2 =  0 ; E2C2 =  1 ;
            # 1 E2A2 =  1 ; E2B2 =  1 ; E2C2 =  0 ;
            # 1 E2A2 =  1 ; E2B2 =  1 ; E2C2 =  1 ;

        end

// Ejercicio 2 - Ecuación 3

        initial begin
            #72
            $display ("\n");
            $display("A B C D | Y");
            $display("--------|--");
            $monitor("%b %b %b %b | %b", E2A3, E2B3, E2C3, E2D3, E2F3);
            E2A3 =  0 ; E2B3 =  0 ; E2C3 =  0 ; E2D3 =  0 ;
            # 1 E2A3 =  0 ; E2B3 =  0 ; E2C3 =  0 ; E2D3 =  1 ; //1
            # 1 E2A3 =  0 ; E2B3 =  0 ; E2C3 =  1 ; E2D3 =  0 ; //2
            # 1 E2A3 =  0 ; E2B3 =  0 ; E2C3 =  1 ; E2D3 =  1 ; //3
            # 1 E2A3 =  0 ; E2B3 =  1 ; E2C3 =  0 ; E2D3 =  0 ; //4 
            # 1 E2A3 =  0 ; E2B3 =  1 ; E2C3 =  0 ; E2D3 =  1 ; //5
            # 1 E2A3 =  0 ; E2B3 =  1 ; E2C3 =  1 ; E2D3 =  0 ; //6
            # 1 E2A3 =  0 ; E2B3 =  1 ; E2C3 =  1 ; E2D3 =  1 ; //7
            # 1 E2A3 =  1 ; E2B3 =  0 ; E2C3 =  0 ; E2D3 =  0 ; //8
            # 1 E2A3 =  1 ; E2B3 =  0 ; E2C3 =  0 ; E2D3 =  1 ; //9
            # 1 E2A3 =  1 ; E2B3 =  0 ; E2C3 =  1 ; E2D3 =  0 ; //10
            # 1 E2A3 =  1 ; E2B3 =  0 ; E2C3 =  1 ; E2D3 =  1 ; //11    
            # 1 E2A3 =  1 ; E2B3 =  1 ; E2C3 =  0 ; E2D3 =  0 ; //12
            # 1 E2A3 =  1 ; E2B3 =  1 ; E2C3 =  0 ; E2D3 =  1 ; //13
            # 1 E2A3 =  1 ; E2B3 =  1 ; E2C3 =  1 ; E2D3 =  0 ; //14
            # 1 E2A3 =  1 ; E2B3 =  1 ; E2C3 =  1 ; E2D3 =  1 ; //15      
           
        end

// Ejercicio 2 - Ecuación 4

        initial begin
            #90 
            $display ("\n");
            $display("A B C | Y");
            $display("------|--");
            $monitor("%b %b %b | %b", E2A4, E2B4, E2C4, E2F4);
            E2A4 =  0 ; E2B4 =  0 ; E2C4 =  0 ;
            # 1 E2A4 =  0 ; E2B4 =  0 ; E2C4 =  1 ;
            # 1 E2A4 =  0 ; E2B4 =  1 ; E2C4 =  0 ;
            # 1 E2A4 =  0 ; E2B4 =  1 ; E2C4 =  1 ;
            # 1 E2A4 =  1 ; E2B4 =  0 ; E2C4 =  0 ;
            # 1 E2A4 =  1 ; E2B4 =  0 ; E2C4 =  1 ;
            # 1 E2A4 =  1 ; E2B4 =  1 ; E2C4 =  0 ;
            # 1 E2A4 =  1 ; E2B4 =  1 ; E2C4 =  1 ;   

        end

        initial 
        #100 $finish;

initial 
    begin
        $dumpfile("codigo_tb.vcd");
        $dumpvars(0,testbench);
    end
endmodule                   //Fin del modulo

Lab4_Digital1/Ejercicio 4/codigo_tb.vcd
$date
	Sat Aug 08 23:00:33 2020
$end
$version
	Icarus Verilog
$end
$timescale
	1ps
$end
$scope module testbench $end
$var wire 1 ! E2F4 $end
$var wire 1 " E2F3 $end
$var wire 1 # E2F2 $end
$var wire 1 $ E2F1 $end
$var wire 1 % E1F4 $end
$var wire 1 & E1F3 $end
$var wire 1 ' E1F2 $end
$var wire 1 ( E1F1 $end
$var reg 1 ) E1A1 $end
$var reg 1 * E1A2 $end
$var reg 1 + E1A3 $end
$var reg 1 , E1A4 $end
$var reg 1 - E1B1 $end
$var reg 1 . E1B2 $end
$var reg 1 / E1B3 $end
$var reg 1 0 E1B4 $end
$var reg 1 1 E1C1 $end
$var reg 1 2 E1C2 $end
$var reg 1 3 E1C3 $end
$var reg 1 4 E1C4 $end
$var reg 1 5 E1D3 $end
$var reg 1 6 E1D4 $end
$var reg 1 7 E2A1 $end
$var reg 1 8 E2A2 $end
$var reg 1 9 E2A3 $end
$var reg 1 : E2A4 $end
$var reg 1 ; E2B1 $end
$var reg 1 < E2B2 $end
$var reg 1 = E2B3 $end
$var reg 1 > E2B4 $end
$var reg 1 ? E2C1 $end
$var reg 1 @ E2C2 $end
$var reg 1 A E2C3 $end
$var reg 1 B E2C4 $end
$var reg 1 C E2D1 $end
$var reg 1 D E2D3 $end
$scope module e1 $end
$var wire 1 $ F $end
$var wire 1 7 inA $end
$var wire 1 ; inB $end
$var wire 1 ? inC $end
$var wire 1 C inD $end
$upscope $end
$scope module e2 $end
$var wire 1 # F $end
$var wire 1 8 inA $end
$var wire 1 < inB $end
$var wire 1 @ inC $end
$upscope $end
$scope module e3 $end
$var wire 1 " F $end
$var wire 1 9 inA $end
$var wire 1 = inB $end
$var wire 1 A inC $end
$var wire 1 D inD $end
$upscope $end
$scope module e4 $end
$var wire 1 ! F $end
$var wire 1 : inA $end
$var wire 1 > inB $end
$var wire 1 B inC $end
$upscope $end
$scope module t1 $end
$var wire 1 ( F $end
$var wire 1 E a1 $end
$var wire 1 F a2 $end
$var wire 1 G a3 $end
$var wire 1 ) inA $end
$var wire 1 - inB $end
$var wire 1 1 inC $end
$var wire 1 H n1 $end
$var wire 1 I n2 $end
$var wire 1 J n3 $end
$upscope $end
$scope module t2 $end
$var wire 1 ' F $end
$var wire 1 * inA $end
$var wire 1 . inB $end
$var wire 1 2 inC $end
$var wire 1 K n2 $end
$upscope $end
$scope module t3 $end
$var wire 1 & F $end
$var wire 1 L a1 $end
$var wire 1 M a2 $end
$var wire 1 N a3 $end
$var wire 1 O a4 $end
$var wire 1 P a5 $end
$var wire 1 Q a6 $end
$var wire 1 R a7 $end
$var wire 1 S a8 $end
$var wire 1 + inA $end
$var wire 1 / inB $end
$var wire 1 3 inC $end
$var wire 1 5 inD $end
$var wire 1 T n1 $end
$var wire 1 U n2 $end
$var wire 1 V n3 $end
$var wire 1 W n4 $end
$upscope $end
$scope module t4 $end
$var wire 1 % F $end
$var wire 1 X a1 $end
$var wire 1 Y a2 $end
$var wire 1 Z a3 $end
$var wire 1 [ a4 $end
$var wire 1 \ a5 $end
$var wire 1 , inA $end
$var wire 1 0 inB $end
$var wire 1 4 inC $end
$var wire 1 6 inD $end
$var wire 1 ] n1 $end
$var wire 1 ^ n2 $end
$var wire 1 _ n3 $end
$var wire 1 ` n4 $end
$upscope $end
$upscope $end
$enddefinitions $end
#0
$dumpvars
x`
x_
x^
x]
x\
x[
xZ
xY
xX
xW
xV
xU
xT
xS
xR
xQ
xP
xO
xN
xM
xL
xK
1J
1I
1H
0G
0F
1E
xD
xC
xB
xA
x@
x?
x>
x=
x<
x;
x:
x9
x8
x7
x6
x5
x4
x3
x2
01
x0
x/
x.
0-
x,
x+
x*
0)
1(
x'
x&
x%
x$
x#
x"
x!
$end
#1
0(
0E
0J
11
#2
1(
1E
1J
0I
01
1-
#3
0(
0E
0J
11
#4
1(
1G
1J
1I
0H
01
0-
1)
#5
0J
1F
11
#6
0(
0G
1J
0F
0I
01
1-
#7
1(
0J
1F
11
#8
1'
1K
02
0.
0*
#9
12
#10
0'
0K
02
1.
#11
12
#12
1'
1K
02
0.
1*
#13
12
#14
0'
0K
02
1.
#15
12
#16
1&
1L
1W
1V
0M
1U
0N
0O
1T
0P
0Q
0R
0S
05
03
0/
0+
#17
0&
0L
0W
15
#18
1W
0V
05
13
#19
1&
0W
1M
15
#20
0&
1W
1V
0M
0U
05
03
1/
#21
1&
0W
1N
15
#22
1&
1O
1W
0N
0V
05
13
#23
0&
0O
0W
15
#24
1W
1V
1U
0T
05
03
0/
1+
#25
1&
0W
1R
15
#26
1&
1S
1W
0R
0V
05
13
#27
0&
0S
0W
15
#28
1&
1P
1W
1V
0U
05
03
1/
#29
0&
0P
0W
15
#30
1W
0V
05
13
#31
1&
0W
1Q
15
#32
1%
1X
1`
0Y
1_
1^
0Z
1]
0[
0\
06
04
00
0,
#33
0X
0`
1Y
16
#34
1%
1X
1`
0Y
0_
06
14
#35
0%
0X
0`
16
#36
1`
1_
0^
06
04
10
#37
1%
0`
1Y
1Z
16
#38
0%
1`
0Y
0Z
0_
06
14
#39
1%
0`
1Z
16
#40
1%
1[
1`
1_
1^
0Z
0]
06
04
00
1,
#41
0%
0[
0`
16
#42
1%
1`
0_
1\
06
14
#43
0`
16
#44
1%
1[
1`
1_
0\
0^
06
04
10
#45
0[
0`
1Z
16
#46
1`
0Z
0_
1\
06
14
#47
0`
1Z
16
#48
1$
0C
0?
0;
07
#49
0$
1C
#50
0C
1?
#51
1C
#52
0C
0?
1;
#53
1C
#54
0C
1?
#55
1C
#56
1$
0C
0?
0;
17
#57
1C
#58
0C
1?
#59
1C
#60
1$
0C
0?
1;
#61
1C
#62
0C
1?
#63
0$
1C
#64
1#
0@
0<
08
#65
1@
#66
0#
0@
1<
#67
1@
#68
1#
0@
0<
18
#69
1@
#70
0#
0@
1<
#71
1#
1@
#72
0"
0D
0A
0=
09
#73
1"
1D
#74
0"
0D
1A
#75
1D
#76
1"
0D
0A
1=
#77
1D
#78
0D
1A
#79
1D
#80
0"
0D
0A
0=
19
#81
1"
1D
#82
0"
0D
1A
#83
1"
1D
#84
0D
0A
1=
#85
1D
#86
0D
1A
#87
1D
#90
1!
0B
0>
0:
#91
0!
1B
#92
1!
0B
1>
#93
1B
#94
0!
0B
0>
1:
#95
1B
#96
1!
0B
1>
#97
1B
