Lab9_Digital1/Ejercicio4/Ejercicio4.v
// Luis Pedro Molina Velásquez
// Carné 18822 - Sección 12
// Laboratorio 9 
// Ejercicio 4 - Buffer triestado de 4 bits

module Buffer3_1B (A, enable, Y);
input [3:0]A; input enable; 
output reg [3:0]Y;

always @ (*)
    if (enable) begin
        Y<=A;
    end
    else begin 
        Y <=4'bzzzz;
    end

endmodule

Lab9_Digital1/Ejercicio4/Ejercicio4_tb.v
// Luis Pedro Molina Velásquez
// Carné 18822 - Sección 12
// Laboratorio 9 
// Ejercicio 4 - Buffer triestado de 4 bits

module testbench();

reg [3:0]A;  reg enable;
wire [3:0]Y;

Buffer3_1B buffer3_1b(A, enable, Y);


    initial begin
        
        #1 
        $display (" ");
        $display(" Ejercicio 4 - Buffer Triestado ");
        $display(" ");
        $display(" Enable  Input A |  Output Y ");
        $display("----------------|-----------");
        $monitor(" %b        %b   |  %b", enable, A, Y);
           enable = 0 ; A = 4'b0000 ;
        #1 enable = 0 ; A = 4'b1100 ;
        #1 enable = 0 ; A = 4'b1111 ;
        #1 enable = 1 ; A = 4'b0100 ;
        #1 enable = 1 ; A = 4'b1011 ;
        #1 enable = 0 ; A = 4'b1100 ;
        #1 enable = 0 ; A = 4'b1100 ;
        #1 enable = 1 ; A = 4'b1110 ;
        
    end

    initial
    #15  $finish;

initial

    begin
        $dumpfile("Ejercicio4_tb.vcd");
        $dumpvars(0, testbench);
    end

endmodule

Lab9_Digital1/Ejercicio4/Ejercicio4_tb.vcd
$date
	Sat Oct 31 08:12:38 2020
$end
$version
	Icarus Verilog
$end
$timescale
	1ps
$end
$scope module testbench $end
$var wire 4 ! Y [3:0] $end
$var reg 4 " A [3:0] $end
$var reg 1 # enable $end
$scope module buffer3_1b $end
$var wire 4 $ A [3:0] $end
$var wire 1 # enable $end
$var reg 4 % Y [3:0] $end
$upscope $end
$upscope $end
$enddefinitions $end
#0
$dumpvars
bx %
bx $
x#
bx "
bx !
$end
#1
bz !
bz %
b0 "
b0 $
0#
#2
b1100 "
b1100 $
#3
b1111 "
b1111 $
#4
b100 !
b100 %
b100 "
b100 $
1#
#5
b1011 !
b1011 %
b1011 "
b1011 $
#6
bz !
bz %
b1100 "
b1100 $
0#
#8
b1110 !
b1110 %
b1110 "
b1110 $
1#
