Lab9_Digital1/Ejercicio2/Ejercicio2.v
// Luis Pedro Molina Velásquez
// Carné 18822 - Sección 12
// Laboratorio 9 
// Ejercicio 2 - Flip Flop tipo T

// Flip Flop tipo D de 1 bit
module FFD1B (input wire D, input wire clk, input wire reset, input wire enable, output reg Q);

    always @ (posedge clk or posedge reset) begin
        if (reset)
            Q <= 1'b0;
        else if (enable)
            Q <= D; 
    end

endmodule 

// Flip Flop tipo T de 1 bit
module FFTT1B (input wire clk, input wire reset, input wire enable, output Q);
FFD1B ffd1b (~Q, clk, reset, enable, Q);

endmodule

Lab9_Digital1/Ejercicio2/Ejercicio2_tb.v
// Luis Pedro Molina Velásquez
// Carné 18822 - Sección 12
// Laboratorio 9 
// Ejercicio 1 - Flip Flop tipo T

module testbench ();

reg clk, reset, enable;
wire Q;

FFTT1B fftt1b (clk, reset, enable, Q);

initial begin
    clk = 1 ; 
    forever #1 clk = ~clk ;
end

    initial begin
        
        #1 
        $display (" ");
        $display(" Ejercicio 2 - Flip Flop tipo T");
        $display(" ");
        $display(" Reset  Enable  |  Q ");
        $display("---------------|-----");
        $monitor("  %b        %b     |  %b", reset, enable, Q);
           reset = 0 ; enable = 0 ;
        #1 reset = 1 ; enable = 0 ; 
        #1 reset = 0 ; enable = 1 ; 
        #1 reset = 0 ; enable = 0 ;
        #1 reset = 0 ; enable = 0 ;
        #1 reset = 0 ; enable = 1 ;
        #1 reset = 0 ; enable = 1 ;
        #1 reset = 0 ; enable = 1 ;
        #1 reset = 0 ; enable = 1 ;
        #1 reset = 1 ; enable = 0 ;
        #1 reset = 0 ; enable = 0 ;
        #1 reset = 0 ; enable = 1 ;
        #1 reset = 0 ; enable = 1 ;
        #1 reset = 0 ; enable = 1 ;
    
    
    end

    initial
    #30  $finish;

initial
    begin
        $dumpfile("Ejercicio2_tb.vcd");
        $dumpvars(0, testbench);
    end

endmodule

Lab9_Digital1/Ejercicio2/Ejercicio2_tb.vcd
$date
	Sat Oct 31 02:30:13 2020
$end
$version
	Icarus Verilog
$end
$timescale
	1ps
$end
$scope module testbench $end
$var wire 1 ! Q $end
$var reg 1 " clk $end
$var reg 1 # enable $end
$var reg 1 $ reset $end
$scope module fftt1b $end
$var wire 1 " clk $end
$var wire 1 # enable $end
$var wire 1 $ reset $end
$var wire 1 ! Q $end
$scope module ffd1b $end
$var wire 1 % D $end
$var wire 1 " clk $end
$var wire 1 # enable $end
$var wire 1 $ reset $end
$var reg 1 ! Q $end
$upscope $end
$upscope $end
$upscope $end
$enddefinitions $end
#0
$dumpvars
x%
x$
x#
1"
x!
$end
#1
0#
0$
0"
#2
1%
0!
1$
1"
#3
1#
0$
0"
#4
0#
1"
#5
0"
#6
0%
1!
1#
1"
#7
0"
#8
1%
0!
1"
#9
0"
#10
0#
1$
1"
#11
0$
0"
#12
0%
1!
1#
1"
#13
0"
#14
1%
0!
1"
#15
0"
#16
0%
1!
1"
#17
0"
#18
1%
0!
1"
#19
0"
#20
0%
1!
1"
#21
0"
#22
1%
0!
1"
#23
0"
#24
0%
1!
1"
#25
0"
#26
1%
0!
1"
#27
0"
#28
0%
1!
1"
#29
0"
#30
1%
0!
1"
