Circuito4_POS/Tabla4_POS.v

// Luis Pedro Molina Velasquez
// Carne 18822 - Seccion 12

// Tabla 4 - POS

module gates ();
    //wire n0 al n3 definidos para not   
    //wire a3 al a11 definidos para or
    //wire F para salida final
    wire n0;
    wire n1;
    wire n2;
    wire n3;
    wire a3;
    wire a4;
    wire a5;
    wire a6;
    wire a7;
    wire a8;
    wire a9;
    wire a10;
    wire a11;
    wire F;

    reg inA,inB,inC,inD; 

    not z1 (n0,inA);  //-A
    not z2 (n1,inB);  //-B
    not z3 (n2,inC);  //-C
    not z4 (n3,inD);  //-D

    or x1 (a3,inA,inB,inC,n3);
    or x2 (a4,inA,n1,inC,inD);
    or x3 (a5,inA,n1,inC,n3);
    or x4 (a6,n0,inB,inC,n3);
    or x5 (a7,n0,inB,n2,n3);
    or x6 (a8,n0,n1,inC,inD);
    or x7 (a9,n0,n1,inC,n3);
    or x8 (a10,n0,n1,n2,inD);
    or x9 (a11,n0,n1,n2,n3);

    and k1 (F,a3,a4,a5,a6,a7,a8,a9,a10,a11);

initial begin
    $display("A B C D| Y");
    $display("-------| -");
    $monitor("%b %b %b %b | %b",inA, inB, inC, inD, F);
    
      //Condicion inicial
    inA = 0;
    inB = 0;
    inC = 0;
    inD = 0;
    //Combinacion de simulaciones
    #1 inD = 1;
    #1 inC = 1; inD = 0;
    #1 inD = 1;
    #1 inB = 1; inC = 0; inD = 0;
    #1 inD = 1;
    #1 inC = 1; inD = 0;
    #1 inD = 1;
    #1 inA = 1; inB = 0; inC = 0; inD = 0;
    #1 inD = 1;
    #1 inC = 1; inD = 0;
    #1 inD = 1;
    #1 inB = 1; inC = 0; inD = 0;
    #1 inD = 1;
    #1 inC = 1; inD = 0;
    #1 inD = 1; 
    #1 $finish;             //Finaliza la simulacion

end
initial 
    begin
        $dumpfile("Tabla4_POS_tb.vcd");
        $dumpvars(0,gates);
    end
endmodule                   //Fin del modulo

Circuito4_POS/Tabla4_POS_tb.vcd
$date
	Sat Aug 01 21:40:38 2020
$end
$version
	Icarus Verilog
$end
$timescale
	1ps
$end
$scope module gates $end
$var wire 1 ! F $end
$var wire 1 " a10 $end
$var wire 1 # a11 $end
$var wire 1 $ a3 $end
$var wire 1 % a4 $end
$var wire 1 & a5 $end
$var wire 1 ' a6 $end
$var wire 1 ( a7 $end
$var wire 1 ) a8 $end
$var wire 1 * a9 $end
$var wire 1 + n0 $end
$var wire 1 , n1 $end
$var wire 1 - n2 $end
$var wire 1 . n3 $end
$var reg 1 / inA $end
$var reg 1 0 inB $end
$var reg 1 1 inC $end
$var reg 1 2 inD $end
$upscope $end
$enddefinitions $end
#0
$dumpvars
02
01
00
0/
1.
1-
1,
1+
1*
1)
1(
1'
1&
1%
1$
1#
1"
1!
$end
#1
0!
0$
0.
12
#2
1!
1.
1$
0-
02
11
#3
0.
12
#4
0!
1.
1&
0%
1-
0,
02
01
10
#5
0&
1%
0.
12
#6
1!
1.
1&
0-
02
11
#7
0.
12
#8
1!
1.
1-
1(
1'
1,
0+
02
01
00
1/
#9
0!
0'
0.
12
#10
1!
1.
1'
0-
02
11
#11
0!
0(
0.
12
#12
1.
1*
0)
1-
1(
0,
02
01
10
#13
0*
1)
0.
12
#14
0"
1.
1*
0-
02
11
#15
0#
1"
0.
12
