Lab9_Digital1/Ejercicio3/Ejercicio3.v
// Luis Pedro Molina Velásquez
// Carné 18822 - Sección 12
// Laboratorio 9 
// Ejercicio 3 - Flip Flop tipo JK

// Flip Flop tipo D de 1 bit
module FFD1B (input wire D, input wire clk, input wire reset, input wire enable, output reg Q);

    always @ (posedge clk or posedge reset) begin
        if (reset)
            Q <= 1'b0;
        else if (enable)
            Q <= D; 
    end

endmodule 

// Flip Flop tipo JK de 1 bit
module FFJK1B (input wire clk, input wire reset, input wire enable, input wire J, input wire K, output Q);

    wire NK, NQ, JaNQ, NKaQ, D;
    not (NK, K);
    not (NQ, Q);
    and (JaNQ, J, NQ);
    and (NKaQ, NK, Q);
    or  (D, JaNQ, NKaQ);

    FFD1B ffd1b (D, clk, reset, enable, Q);

endmodule

Lab9_Digital1/Ejercicio3/Ejercicio3_tb.v
// Luis Pedro Molina Velásquez
// Carné 18822 - Sección 12
// Laboratorio 9 
// Ejercicio 3 - Flip Flop tipo JK

module testbench ();

reg clk, reset, enable, J, K;
wire Q;

FFJK1B ffjk1b (clk, reset, enable, J, K, Q);

initial begin
    clk = 1 ; 
    forever #1 clk = ~clk ;
end

    initial begin
        
        #1 
        $display (" ");
        $display(" Ejercicio 3 - Flip Flop tipo JK ");
        $display(" ");
        $display(" T  Reset  Enable    J    K  |  Q ");
        $display("----------------------------|-----");
        $monitor(" %b   %b        %b      %b    %b  |  %b", clk, reset, enable, J, K, Q);

        // Prueba de que cuando J y K = 1 --> Q = ~Q
           reset = 0 ; enable = 0 ; J = 0 ; K = 0 ;
        #1 reset = 1 ; enable = 0 ; J = 0 ; K = 0 ;
        #1 reset = 0 ; enable = 0 ; J = 0 ; K = 0 ;
        #1 reset = 0 ; enable = 1 ; J = 0 ; K = 0 ;
        #1 reset = 0 ; enable = 1 ; J = 0 ; K = 0 ;
        #1 reset = 0 ; enable = 1 ; J = 1 ; K = 1 ; 
        #1 reset = 0 ; enable = 1 ; J = 1 ; K = 1 ;
        #1 reset = 0 ; enable = 1 ; J = 1 ; K = 1 ;
        #1 reset = 0 ; enable = 1 ; J = 1 ; K = 1 ;
        #1 reset = 0 ; enable = 1 ; J = 1 ; K = 1 ;
        #1 reset = 0 ; enable = 1 ; J = 1 ; K = 1 ;
        #1 reset = 0 ; enable = 1 ; J = 1 ; K = 1 ;
        #1 reset = 0 ; enable = 1 ; J = 1 ; K = 1 ;
        #1 reset = 0 ; enable = 1 ; J = 1 ; K = 1 ;
        #1 reset = 0 ; enable = 1 ; J = 1 ; K = 1 ;
        // Prueba de que cuando J y K = 0 --> Q = Mantiene el último valor 
        #1 reset = 0 ; enable = 1 ; J = 0 ; K = 0 ;
        #1 reset = 0 ; enable = 1 ; J = 0 ; K = 0 ;
        #1 reset = 0 ; enable = 1 ; J = 0 ; K = 0 ;
        // Prueba de que cuando J = 0 y K = 1 --> Q = 0 
        #1 reset = 0 ; enable = 1 ; J = 0 ; K = 1 ;
        #1 reset = 0 ; enable = 1 ; J = 0 ; K = 1 ;
        #1 reset = 0 ; enable = 1 ; J = 0 ; K = 1 ;
        // Prueba de que cuando J = 1 y K = 0 --> Q = 1
        #1 reset = 0 ; enable = 1 ; J = 0 ; K = 0 ;
        #1 reset = 0 ; enable = 1 ; J = 1 ; K = 0 ;
        #1 reset = 0 ; enable = 1 ; J = 1 ; K = 0 ;
        #1 reset = 0 ; enable = 1 ; J = 1 ; K = 0 ;
        // Prueba de que enable = 0 --> Q no hace nada, se queda en el último valor
        #1 reset = 0 ; enable = 0 ; J = 1 ; K = 1 ;
        #1 reset = 0 ; enable = 0 ; J = 1 ; K = 0 ;
        
    end

    initial
    #30  $finish;

initial

    begin
        $dumpfile("Ejercicio3_tb.vcd");
        $dumpvars(0, testbench);
    end

endmodule

Lab9_Digital1/Ejercicio3/Ejercicio3_tb.vcd
$date
	Sat Oct 31 08:04:50 2020
$end
$version
	Icarus Verilog
$end
$timescale
	1ps
$end
$scope module testbench $end
$var wire 1 ! Q $end
$var reg 1 " J $end
$var reg 1 # K $end
$var reg 1 $ clk $end
$var reg 1 % enable $end
$var reg 1 & reset $end
$scope module ffjk1b $end
$var wire 1 ' D $end
$var wire 1 " J $end
$var wire 1 ( JaNQ $end
$var wire 1 # K $end
$var wire 1 ) NK $end
$var wire 1 * NKaQ $end
$var wire 1 + NQ $end
$var wire 1 $ clk $end
$var wire 1 % enable $end
$var wire 1 & reset $end
$var wire 1 ! Q $end
$scope module ffd1b $end
$var wire 1 ' D $end
$var wire 1 $ clk $end
$var wire 1 % enable $end
$var wire 1 & reset $end
$var reg 1 ! Q $end
$upscope $end
$upscope $end
$upscope $end
$enddefinitions $end
#0
$dumpvars
x+
x*
x)
x(
x'
x&
x%
1$
x#
x"
x!
$end
#1
1)
0(
0#
0"
0%
0&
0$
#2
0'
0*
1+
0!
1&
1$
#3
0&
0$
#4
1%
1$
#5
0$
#6
1'
0)
1(
1#
1"
1$
#7
0$
#8
0'
0(
0+
1!
1$
#9
0$
#10
1'
1(
1+
0!
1$
#11
0$
#12
0'
0(
0+
1!
1$
#13
0$
#14
1'
1(
1+
0!
1$
#15
0$
#16
1*
0+
1!
1'
1)
0(
0#
0"
1$
#17
0$
#18
1$
#19
0'
0*
0)
1#
0$
#20
1+
0!
1$
#21
0$
#22
1)
0#
1$
#23
1'
1(
1"
0$
#24
0(
1*
0+
1!
1$
#25
0$
#26
0'
0*
0)
1#
0%
1$
#27
1'
1*
1)
0#
0$
