Lab8_Digital1/Ejercicio3-ALU/ALU.v
// Luis Pedro Molina Velásquez
// Carné 18822 - Sección 12
// Laboratorio 8
// Ejercicio 3 - ALU

module ALU (input wire [3:0]A, input wire [3:0]B, input wire [2:0]Comando, output reg [3:0]Resultado);

   always @ (A or B or Comando) begin
      
      case(Comando)
         3'b000: Resultado = A + B ;  // Suma
         3'b001: Resultado = A - B ;  // Resta
         3'b010: Resultado = A & B ;  // AND
         3'b100: Resultado = A | B ;  // OR
         3'b101: Resultado = A & ~B;  // A AND ~B
         3'b110: Resultado = ~A | B;  // ~A or B
         3'b111: Resultado = (A < B) ? 1:0; // // Comparación de A mayor a B
         default: Resultado = 4'b0000 ;
      endcase

   end
endmodule

Lab8_Digital1/Ejercicio3-ALU/ALU_tb.v
// Luis Pedro Molina Velásquez
// Carné 18822 - Sección 12
// Laboratorio 8
// Ejercicio 3 - ALU

module testbench ();

reg [3:0]A ; reg [3:0]B ; reg [2:0]Comando ; 
wire [3:0]Resultado ;

ALU alu(A, B, Comando, Resultado);

initial begin
    
    #1
    $display(" ");
    $display(" ALU ");
    $display(" ");
    $display(" A       B     COM  | RESULTADO");
    $display(" -------------------|-----------");
    $monitor(" %b   %b   %b     %b    ", A, B, Comando, Resultado);
       A = 4'b0000 ; B = 4'b0000 ; Comando = 3'b000 ;
    #1 A = 4'b0001 ; B = 4'b0010 ; Comando = 3'b000 ;  // 1 + 2 = 3
    #1 A = 4'b1000 ; B = 4'b0110 ; Comando = 3'b000 ;  // 8 + 6 = 14
    #1 A = 4'b1111 ; B = 4'b0011 ; Comando = 3'b001 ;  // 15 - 3 = 12
    #1 A = 4'b0011 ; B = 4'b0001 ; Comando = 3'b001 ;  // 3 - 1 = 2
    #1 A = 4'b1011 ; B = 4'b0010 ; Comando = 3'b010 ;  // A & B = 0010
    #1 A = 4'b0110 ; B = 4'b1111 ; Comando = 3'b010 ;  // A & B = 0110
    #1 A = 4'b0001 ; B = 4'b0010 ; Comando = 3'b100 ;  // A | B = 0011
    #1 A = 4'b0000 ; B = 4'b0100 ; Comando = 3'b100 ;  // A | B = 0100
    #1 A = 4'b1010 ; B = 4'b0101 ; Comando = 3'b101 ;  // A &~B = 1010
    #1 A = 4'b1111 ; B = 4'b0010 ; Comando = 3'b101 ;  // A &~B = 1101
    #1 A = 4'b1011 ; B = 4'b0000 ; Comando = 3'b110 ;  // ~A| B = 0100
    #1 A = 4'b1000 ; B = 4'b0001 ; Comando = 3'b110 ;  // ~A| B = 0111
    #1 A = 4'b1000 ; B = 4'b0000 ; Comando = 3'b111 ;  // A < B = 0000
    #1 A = 4'b0010 ; B = 4'b1000 ; Comando = 3'b111 ;  // A < B = 0001

end

    initial
    #15 $finish;

initial 
    begin
        $dumpfile("ALU_tb.vcd");
        $dumpvars(0,testbench);
    end

endmodule

Lab8_Digital1/Ejercicio3-ALU/ALU_tb.vcd
$date
	Sat Oct 24 23:24:09 2020
$end
$version
	Icarus Verilog
$end
$timescale
	1ps
$end
$scope module testbench $end
$var wire 4 ! Resultado [3:0] $end
$var reg 4 " A [3:0] $end
$var reg 4 # B [3:0] $end
$var reg 3 $ Comando [2:0] $end
$scope module alu $end
$var wire 4 % A [3:0] $end
$var wire 4 & B [3:0] $end
$var wire 3 ' Comando [2:0] $end
$var reg 4 ( Resultado [3:0] $end
$upscope $end
$upscope $end
$enddefinitions $end
#0
$dumpvars
bx (
bx '
bx &
bx %
bx $
bx #
bx "
bx !
$end
#1
b0 !
b0 (
b0 $
b0 '
b0 #
b0 &
b0 "
b0 %
#2
b11 !
b11 (
b10 #
b10 &
b1 "
b1 %
#3
b1110 !
b1110 (
b110 #
b110 &
b1000 "
b1000 %
#4
b1100 !
b1100 (
b1 $
b1 '
b11 #
b11 &
b1111 "
b1111 %
#5
b10 !
b10 (
b1 #
b1 &
b11 "
b11 %
#6
b10 $
b10 '
b10 #
b10 &
b1011 "
b1011 %
#7
b110 !
b110 (
b1111 #
b1111 &
b110 "
b110 %
#8
b11 !
b11 (
b100 $
b100 '
b10 #
b10 &
b1 "
b1 %
#9
b100 !
b100 (
b100 #
b100 &
b0 "
b0 %
#10
b1010 !
b1010 (
b101 $
b101 '
b101 #
b101 &
b1010 "
b1010 %
#11
b1101 !
b1101 (
b10 #
b10 &
b1111 "
b1111 %
#12
b100 !
b100 (
b110 $
b110 '
b0 #
b0 &
b1011 "
b1011 %
#13
b111 !
b111 (
b1 #
b1 &
b1000 "
b1000 %
#14
b0 !
b0 (
b111 $
b111 '
b0 #
b0 &
#15
b1 !
b1 (
b1000 #
b1000 &
b10 "
b10 %
