Lab9_Digital1/Ejercicio5/Ejercicio5.v
// Luis Pedro Molina Velásquez
// Carné 18822 - Sección 12
// Laboratorio 9 
// Ejercicio 5 - Implementación de memoria ROM

module ROM_implementation (input wire enable, input wire [6:0]Input, output reg [6:0]Output);

    always @ (enable or Input)begin
            Output = 0 ;
        if (enable)

            casex (Input)
                7'bxxxxxx0: Output <= 13'b1000000001000;
                7'b00001x1: Output <= 13'b0100000001000;
                7'b00000x1: Output <= 13'b1000000001000;
                7'b00011x1: Output <= 13'b1000000001000;
                7'b00010x1: Output <= 13'b1000000001000;
                7'b0010xx1: Output <= 13'b1000000001000;
                7'b0011xx1: Output <= 13'b1000000001000;
                7'b0100xx1: Output <= 13'b0011010000010;
                7'b0101xx1: Output <= 13'b0011010000100;
                7'b0110xx1: Output <= 13'b1011010100000;
                7'b0111xx1: Output <= 13'b1000000111000;
                7'b1000x11: Output <= 13'b0100000001000;
                7'b1000x01: Output <= 13'b1000000001000;
                7'b1001x11: Output <= 13'b1000000001000;
                7'b1001x01: Output <= 13'b0100000001000;
                7'b1010xx1: Output <= 13'b0011011000010;
                7'b1011xx1: Output <= 13'b1011011100000;
                7'b1100xx1: Output <= 13'b0100000001000;
                7'b1101xx1: Output <= 13'b0000000001001;
                7'b1110xx1: Output <= 13'b0011100000010;
                7'b1111xx1: Output <= 13'b1011100100000;

            endcase

    end

endmodule

Lab9_Digital1/Ejercicio5/Ejercicio5_tb.v
// Luis Pedro Molina Velásquez
// Carné 18822 - Sección 12
// Laboratorio 9 
// Ejercicio 5 - Implementación de memoria ROM

module testbench() ;

reg enable ; reg [6:0]Input ;
wire [6:0]Output ;

ROM_implementation rom_i (enable, Input, Output);

    initial begin
        
        #1 
        $display (" ");
        $display(" Ejercicio 5 - Implementacion de memoria ROM ");
        $display(" ");
        $display(" Enable     Input  |  Output  ");
        $display("------------------|-----------");
        $monitor(" %b        %b  |  %b", enable, Input, Output);
           enable = 0 ; Input = 7'b0000000 ;
        #2 enable = 1 ; Input = 7'bxxxxxx0 ;
        #2 enable = 1 ; Input = 7'b0000101 ;
        #2 enable = 1 ; Input = 7'b0101010 ;
        #2 enable = 1 ; Input = 7'b00000x1 ;
        #2 enable = 1 ; Input = 7'b00011x1 ;
        #2 enable = 1 ; Input = 7'b00001x1 ;
        #2 enable = 1 ; Input = 7'b0011xx1 ;
        #2 enable = 1 ; Input = 7'b00011x1 ;
        #2 enable = 1 ; Input = 7'b0010xx1 ;
        #2 enable = 1 ; Input = 7'b0100xx1 ;
        #2 enable = 1 ; Input = 7'b0110xx1 ;
        #2 enable = 1 ; Input = 7'b0101xx1 ;
        #2 enable = 1 ; Input = 7'b1001x01 ;
        #2 enable = 1 ; Input = 7'b0111xx1 ;
        #2 enable = 1 ; Input = 7'b1001x11 ;
        #2 enable = 1 ; Input = 7'b1000x11 ;
        #2 enable = 1 ; Input = 7'b1110xx1 ;
        #2 enable = 1 ; Input = 7'b1000x01 ;
        #2 enable = 1 ; Input = 7'b1010xx1 ;
        #2 enable = 1 ; Input = 7'b1101xx1 ;
        #2 enable = 1 ; Input = 7'b1011xx1 ;
        #2 enable = 1 ; Input = 7'b1100xx1 ;
        #2 enable = 1 ; Input = 7'b0010xx1 ;
        #2 enable = 1 ; Input = 7'b0110xx1 ;
        #2 enable = 1 ; Input = 7'bxxxx1xx ;
        #2 enable = 1 ; Input = 7'b0000xx1 ;
        #2 enable = 1 ; Input = 7'bxx10xx1 ;
        #2 enable = 1 ; Input = 7'b10x10x1 ;
        #2 enable = 1 ; Input = 7'b1x10xx1 ;
        #2 enable = 1 ; Input = 7'b1xx1xx1 ;
        #2 enable = 1 ; Input = 7'b11x1x01 ;


    end

    initial
    #100 $finish;

initial begin
    $dumpfile("Ejercicio5_tb.vcd");
    $dumpvars(0, testbench); 
end

endmodule

Lab9_Digital1/Ejercicio5/Ejercicio5_tb.vcd
$date
	Sat Oct 31 09:09:16 2020
$end
$version
	Icarus Verilog
$end
$timescale
	1ps
$end
$scope module testbench $end
$var wire 7 ! Output [6:0] $end
$var reg 7 " Input [6:0] $end
$var reg 1 # enable $end
$scope module rom_i $end
$var wire 7 $ Input [6:0] $end
$var wire 1 # enable $end
$var reg 7 % Output [6:0] $end
$upscope $end
$upscope $end
$enddefinitions $end
#0
$dumpvars
bx %
bx $
x#
bx "
bx !
$end
#1
b0 !
b0 %
b0 "
b0 $
0#
#3
b1000 !
b1000 %
bx0 "
bx0 $
1#
#5
b1000 !
b1000 %
b101 "
b101 $
#7
b1000 !
b1000 %
b101010 "
b101010 $
#9
b1000 !
b1000 %
b0x1 "
b0x1 $
#11
b1000 !
b1000 %
b11x1 "
b11x1 $
#13
b1000 !
b1000 %
b1x1 "
b1x1 $
#15
b1000 !
b1000 %
b11xx1 "
b11xx1 $
#17
b1000 !
b1000 %
b11x1 "
b11x1 $
#19
b1000 !
b1000 %
b10xx1 "
b10xx1 $
#21
b10 !
b10 %
b100xx1 "
b100xx1 $
#23
b100000 !
b100000 %
b110xx1 "
b110xx1 $
#25
b100 !
b100 %
b101xx1 "
b101xx1 $
#27
b1000 !
b1000 %
b1001x01 "
b1001x01 $
#29
b111000 !
b111000 %
b111xx1 "
b111xx1 $
#31
b1000 !
b1000 %
b1001x11 "
b1001x11 $
#33
b1000 !
b1000 %
b1000x11 "
b1000x11 $
#35
b10 !
b10 %
b1110xx1 "
b1110xx1 $
#37
b1000 !
b1000 %
b1000x01 "
b1000x01 $
#39
b1000010 !
b1000010 %
b1010xx1 "
b1010xx1 $
#41
b1001 !
b1001 %
b1101xx1 "
b1101xx1 $
#43
b1100000 !
b1100000 %
b1011xx1 "
b1011xx1 $
#45
b1000 !
b1000 %
b1100xx1 "
b1100xx1 $
#47
b1000 !
b1000 %
b10xx1 "
b10xx1 $
#49
b100000 !
b100000 %
b110xx1 "
b110xx1 $
#51
b1000 !
b1000 %
bx1xx "
bx1xx $
#53
b1000 !
b1000 %
b0xx1 "
b0xx1 $
#55
b1000 !
b1000 %
bx10xx1 "
bx10xx1 $
#57
b1000 !
b1000 %
b10x10x1 "
b10x10x1 $
#59
b1000010 !
b1000010 %
b1x10xx1 "
b1x10xx1 $
#61
b1000 !
b1000 %
b1xx1xx1 "
b1xx1xx1 $
#63
b1001 !
b1001 %
b11x1x01 "
b11x1x01 $
